LICENSE.txt
README.md
setup.cfg
setup.py
examples/__init__.py
steampy_rework/__init__.py
steampy_rework/chat.py
steampy_rework/client.py
steampy_rework/confirmation.py
steampy_rework/exceptions.py
steampy_rework/guard.py
steampy_rework/login.py
steampy_rework/market.py
steampy_rework/models.py
steampy_rework/test.py
steampy_rework/trade_pages.py
steampy_rework/utils.py
steampy_rework.egg-info/PKG-INFO
steampy_rework.egg-info/SOURCES.txt
steampy_rework.egg-info/dependency_links.txt
steampy_rework.egg-info/requires.txt
steampy_rework.egg-info/top_level.txt