Metadata-Version: 2.1
Name: steampy-rework
Version: 0.0.3
Summary: A Steam lib for trade automation
Home-page: https://github.com/wizzzz9
Author: Viacheslav Patokin
Author-email: viacheslavpatokin@gmail.com
License: MIT
Download-URL: https://github.com/wizzzz9/steampy_rework/tarball/0.0.3
Keywords: steam,trade,steamapi
Platform: UNKNOWN
License-File: LICENSE.txt
